drb/addons/image/sentinel2/_version.py
drb/addons/image/sentinel2/level1c/__init__.py
drb/addons/image/sentinel2/level1c/cortex.yml
drb/addons/image/sentinel2/level2a/__init__.py
drb/addons/image/sentinel2/level2a/cortex.yml
test/__init__.py
test/test_sentinel2_level1c_image.py
test/test_sentinel2_level2a_image.py
drb_image_sentinel2-1.0.0.dist-info/LICENCE.txt
drb_image_sentinel2-1.0.0.dist-info/METADATA
drb_image_sentinel2-1.0.0.dist-info/WHEEL
drb_image_sentinel2-1.0.0.dist-info/entry_points.txt
drb_image_sentinel2-1.0.0.dist-info/top_level.txt
drb_image_sentinel2-1.0.0.dist-info/RECORD
