Metadata-Version: 2.1
Name: drb-image-sentinel2
Version: 1.0.0
Summary: Sentinel-2 Product
Author: GAEL Systems
Author-email: drb-python@gael.fr
License: LGPLv3
Project-URL: Source, https://gitlab.com/drb-python/add-ons/image/add-ons/sentinel2
Classifier: Programming Language :: Python :: 3.8
Classifier: License :: OSI Approved :: GNU Lesser General Public License v3 (LGPLv3)
Requires-Python: >=3.8
License-File: LICENCE.txt
Requires-Dist: drb-topic-sentinel2 ~=1.3.0
Requires-Dist: drb-image ~=1.3.0
Requires-Dist: drb-driver-image ~=1.3.0
Requires-Dist: drb-driver-zip ~=1.3.0
Requires-Dist: drb-xquery ~=1.3.0
